waky/__init__.py
waky/app.py
waky/conf.py
waky/logging_config.py
waky/main.py
waky/static/favicon/android-chrome-192x192.png
waky/static/favicon/android-chrome-512x512.png
waky/static/favicon/apple-touch-icon.png
waky/static/favicon/favicon-16x16.png
waky/static/favicon/favicon-32x32.png
waky/static/favicon/favicon.ico
waky/static/favicon/site.webmanifest
waky/static/fonts/Righteous/OFL.txt
waky/static/fonts/Righteous/Righteous-Regular.ttf
waky/static/style/waky.css
waky/templates/base.html
waky/templates/index.html
waky-0.2.0.dist-info/LICENSE
waky-0.2.0.dist-info/METADATA
waky-0.2.0.dist-info/WHEEL
waky-0.2.0.dist-info/entry_points.txt
waky-0.2.0.dist-info/top_level.txt
waky-0.2.0.dist-info/RECORD
