Metadata-Version: 2.1
Name: waky
Version: 0.2.0
Summary: Waky is a web application to manage Wake-On-Lan supporting devices
Home-page: https://github.com/landier/waky
Author: Nicolas Landier
Author-email: nicolas.landier@gmail.com
License: UNKNOWN
Platform: UNKNOWN
Requires-Python: >=3.6
Requires-Dist: getmac
Requires-Dist: humanize
Requires-Dist: jinja2
Requires-Dist: ping3
Requires-Dist: sanic
